MANIFEST.in
README.md
setup.py
cowin_api/__init__.py
cowin_api/api_client.py
cowin_api/auth.py
cowin_api/exceptions.py
cowin_api/models.py
cowin_api/password_flow_client.py
cowin_api/py.typed
cowin_api.egg-info/PKG-INFO
cowin_api.egg-info/SOURCES.txt
cowin_api.egg-info/dependency_links.txt
cowin_api.egg-info/requires.txt
cowin_api.egg-info/top_level.txt
cowin_api/api/__init__.py
cowin_api/api/appointment_availability_ap_is_api.py
cowin_api/api/authentication_ap_is_api.py
cowin_api/api/beneficiary_registration_ap_is_api.py
cowin_api/api/certificate_ap_is_api.py
cowin_api/api/metadata_ap_is_api.py
cowin_api/api/user_authentication_ap_is_api.py
cowin_api/api/vaccination_appointment_ap_is_api.py