Metadata-Version: 1.0
Name: cowin-api
Version: 1.0.0
Summary: Co-WIN Protected APIs
Home-page: UNKNOWN
Author: UNKNOWN
Author-email: UNKNOWN
License: UNKNOWN
Keywords: Swagger,Co-WIN Protected APIs
Platform: UNKNOWN
